slacker/__init__.py
slacker/utils.py
slacker-0.12.0.dist-info/METADATA
slacker-0.12.0.dist-info/RECORD
slacker-0.12.0.dist-info/WHEEL
slacker-0.12.0.dist-info/top_level.txt
