Metadata-Version: 2.1
Name: slacker
Version: 0.12.0
Summary: Slack API client
Home-page: http://github.com/os/slacker/
Author: Oktay Sancak
Author-email: oktaysancak@gmail.com
License: http://www.apache.org/licenses/LICENSE-2.0
Keywords: slack api
Platform: UNKNOWN
Classifier: Intended Audience :: Developers
Classifier: License :: OSI Approved :: Apache Software License
Classifier: Natural Language :: English
Classifier: Programming Language :: Python
Classifier: Programming Language :: Python :: 2.6
Classifier: Programming Language :: Python :: 2.7
Classifier: Programming Language :: Python :: 3
Classifier: Programming Language :: Python :: 3.3
Classifier: Programming Language :: Python :: 3.4
Classifier: Programming Language :: Python :: 3.5
Classifier: Programming Language :: Python :: 3.6
Classifier: Programming Language :: Python :: 3.7
